cpg_scpi/__init__.py
cpg_scpi/__main__.py
cpg_scpi/test/__init__.py
cpg_scpi-0.4.1.dist-info/LICENSE
cpg_scpi-0.4.1.dist-info/METADATA
cpg_scpi-0.4.1.dist-info/WHEEL
cpg_scpi-0.4.1.dist-info/top_level.txt
cpg_scpi-0.4.1.dist-info/RECORD
