Metadata-Version: 2.1
Name: cpg-scpi
Version: 0.4.1
Summary: Educational client library to use Adafruit Circuit Playground or BBC micro:bit via SCPI protocol in Python3
Home-page: https://github.com/GeorgBraun/cpg_scpi_python
Author: GeorgBraun
Author-email: georg.braun@hm.edu
License: MIT License
Project-URL: Bug Tracker, https://github.com/GeorgBraun/cpg_scpi_python/issues
Classifier: Programming Language :: Python :: 3
Classifier: License :: OSI Approved :: MIT License
Classifier: Operating System :: OS Independent
Requires-Python: >=3.6
License-File: LICENSE
Requires-Dist: pyserial >=3.5
